paitient-ai/__init__.py
paitient-ai/client.py
paitient-ai/api/__init__.py
paitient-ai/aws/__init__.py
paitient-ai/cli/__init__.py
paitient-ai/cli/secure_model_cli.py
paitient-ai/core/__init__.py
paitient-ai/encryption/__init__.py
paitient-ai/models/__init__.py
paitient-ai/utils/__init__.py
paitient-ai/utils/streaming.py
paitient-secure-model/__init__.py
paitient-secure-model/api/__init__.py
paitient-secure-model/aws/__init__.py
paitient-secure-model/cli/__init__.py
paitient-secure-model/core/__init__.py
paitient-secure-model/encryption/__init__.py
paitient-secure-model/models/__init__.py
paitient-secure-model/utils/__init__.py
src/__init__.py
src/main.py
src/api/__init__.py
src/api/api_service.py
src/api/middleware.py
src/api/server.py
src/aws/__init__.py
src/aws/aws_service.py
src/core/__init__.py
src/core/config_service.py
src/core/subscription_service.py
src/encryption/__init__.py
src/encryption/encryption_service.py
src/kubernetes/__init__.py
src/kubernetes/kubernetes_service.py
src/models/__init__.py
src/models/lora_service.py
src/models/model_service.py
paitient_secure_model-0.0.1.dist-info/METADATA
paitient_secure_model-0.0.1.dist-info/WHEEL
paitient_secure_model-0.0.1.dist-info/entry_points.txt
paitient_secure_model-0.0.1.dist-info/top_level.txt
paitient_secure_model-0.0.1.dist-info/RECORD
